[
	{
		"accountId": 922752,
		"revisionDate": 1503689124000,
		"summonerLevel": 30,
		"id": 944756,
		"profileIconId": 2095,
		"name": "MasterFM"
	},
	{
		"accountId": 396619,
		"revisionDate": 1511033517000,
		"summonerLevel": 31,
		"id": 451719,
		"profileIconId": 539,
		"name": "Sahist"
	},
	{
		"accountId": 391203,
		"revisionDate": 1510074780000,
		"summonerLevel": 30,
		"id": 446303,
		"profileIconId": 1394,
		"name": "JBGood23"
	},
	{
		"accountId": 625059,
		"revisionDate": 1509553919000,
		"summonerLevel": 30,
		"id": 642826,
		"profileIconId": 3014,
		"name": "SB Skunk Buddies"
	},
	{
		"accountId": 200747713,
		"revisionDate": 1502738755000,
		"summonerLevel": 30,
		"id": 2543990,
		"profileIconId": 2095,
		"name": "bah gg Math"
	},
	{
		"accountId": 200770830,
		"revisionDate": 1511465877000,
		"summonerLevel": 37,
		"id": 2566543,
		"profileIconId": 3186,
		"name": "tI ghost"
	},
	{
		"accountId": 200685833,
		"revisionDate": 1511316225000,
		"summonerLevel": 35,
		"id": 2489681,
		"profileIconId": 593,
		"name": "SKT Vibaco"
	},
	{
		"accountId": 695106,
		"revisionDate": 1511445425000,
		"summonerLevel": 34,
		"id": 720655,
		"profileIconId": 3186,
		"name": "HeyKappaKappAHey"
	},
	{
		"accountId": 595625,
		"revisionDate": 1496122788000,
		"summonerLevel": 30,
		"id": 640963,
		"profileIconId": 1598,
		"name": "Yuuhlol"
	},
	{
		"accountId": 206198392,
		"revisionDate": 1511439005000,
		"summonerLevel": 37,
		"id": 9986390,
		"profileIconId": 3186,
		"name": "T\u00f4 bad cara"
	},
	{
		"accountId": 211837413,
		"revisionDate": 1508582861000,
		"summonerLevel": 30,
		"id": 18139179,
		"profileIconId": 3006,
		"name": "AmyInBlack"
	},
	{
		"accountId": 201501596,
		"revisionDate": 1511196334000,
		"summonerLevel": 33,
		"id": 3431253,
		"profileIconId": 502,
		"name": "Guilherme100kill"
	},
	{
		"accountId": 200062809,
		"revisionDate": 1511106591000,
		"summonerLevel": 30,
		"id": 1857718,
		"profileIconId": 785,
		"name": "OLDISGRACA 999"
	},
	{
		"accountId": 434492,
		"revisionDate": 1496693082000,
		"summonerLevel": 30,
		"id": 529592,
		"profileIconId": 1130,
		"name": "Last Trick"
	},
	{
		"accountId": 213179697,
		"revisionDate": 1511419303000,
		"summonerLevel": 34,
		"id": 21492256,
		"profileIconId": 3186,
		"name": "SamBjorn"
	},
	{
		"accountId": 205277979,
		"revisionDate": 1511344142000,
		"summonerLevel": 31,
		"id": 9072606,
		"profileIconId": 775,
		"name": "FDEG"
	},
	{
		"accountId": 455251,
		"revisionDate": 1495754834000,
		"summonerLevel": 30,
		"id": 550351,
		"profileIconId": 717,
		"name": "Patolino manco"
	},
	{
		"accountId": 201753098,
		"revisionDate": 1510491282000,
		"summonerLevel": 30,
		"id": 3692790,
		"profileIconId": 780,
		"name": "khrys karyne"
	},
	{
		"accountId": 395126,
		"revisionDate": 1499712908000,
		"summonerLevel": 30,
		"id": 450226,
		"profileIconId": 1665,
		"name": "perfume dagua"
	},
	{
		"accountId": 201710649,
		"revisionDate": 1511102396000,
		"summonerLevel": 33,
		"id": 3596423,
		"profileIconId": 654,
		"name": "NegaoPelado"
	},
	{
		"accountId": 201949588,
		"revisionDate": 1511460368000,
		"summonerLevel": 39,
		"id": 3847733,
		"profileIconId": 3186,
		"name": "Very Best"
	},
	{
		"accountId": 211781495,
		"revisionDate": 1495757021000,
		"summonerLevel": 30,
		"id": 18176296,
		"profileIconId": 1150,
		"name": "kOz7"
	},
	{
		"accountId": 972266,
		"revisionDate": 1508663271000,
		"summonerLevel": 30,
		"id": 1122057,
		"profileIconId": 2090,
		"name": "Sheeep"
	},
	{
		"accountId": 200754649,
		"revisionDate": 1510591780000,
		"summonerLevel": 30,
		"id": 2574603,
		"profileIconId": 683,
		"name": "Nabo God"
	},
	{
		"accountId": 200523537,
		"revisionDate": 1511459190000,
		"summonerLevel": 31,
		"id": 2348387,
		"profileIconId": 3186,
		"name": "KimLyon"
	},
	{
		"accountId": 203184027,
		"revisionDate": 1504291234000,
		"summonerLevel": 30,
		"id": 5166883,
		"profileIconId": 1429,
		"name": "JPBBS"
	},
	{
		"accountId": 213165755,
		"revisionDate": 1511343881000,
		"summonerLevel": 33,
		"id": 21501371,
		"profileIconId": 3186,
		"name": "sleepnswag"
	},
	{
		"accountId": 455544,
		"revisionDate": 1505651249000,
		"summonerLevel": 30,
		"id": 550644,
		"profileIconId": 1456,
		"name": "Sensual"
	},
	{
		"accountId": 201966971,
		"revisionDate": 1511342964000,
		"summonerLevel": 30,
		"id": 3866999,
		"profileIconId": 3193,
		"name": "Eu stuno tu mata"
	},
	{
		"accountId": 861702,
		"revisionDate": 1510985726000,
		"summonerLevel": 30,
		"id": 874127,
		"profileIconId": 3006,
		"name": "PapaRanoico"
	},
	{
		"accountId": 211527444,
		"revisionDate": 1511450466000,
		"summonerLevel": 36,
		"id": 17860168,
		"profileIconId": 3186,
		"name": "jax On fivV"
	},
	{
		"accountId": 210368710,
		"revisionDate": 1495756854000,
		"summonerLevel": 30,
		"id": 15803232,
		"profileIconId": 0,
		"name": "Poteito SA"
	},
	{
		"accountId": 386740,
		"revisionDate": 1510598068000,
		"summonerLevel": 30,
		"id": 441840,
		"profileIconId": 1387,
		"name": "Shrek69"
	},
	{
		"accountId": 201113808,
		"revisionDate": 1511470708000,
		"summonerLevel": 32,
		"id": 2958495,
		"profileIconId": 3186,
		"name": "Marajah"
	},
	{
		"accountId": 200133982,
		"revisionDate": 1509978223000,
		"summonerLevel": 30,
		"id": 1917421,
		"profileIconId": 581,
		"name": "neeeeX"
	},
	{
		"accountId": 1578409,
		"revisionDate": 1511187799000,
		"summonerLevel": 30,
		"id": 1710332,
		"profileIconId": 12,
		"name": "sacola pl\u00e1stica"
	},
	{
		"accountId": 201595935,
		"revisionDate": 1508628482000,
		"summonerLevel": 30,
		"id": 3542636,
		"profileIconId": 1401,
		"name": "Beheaded"
	},
	{
		"accountId": 538654,
		"revisionDate": 1511367274000,
		"summonerLevel": 38,
		"id": 516299,
		"profileIconId": 3168,
		"name": "ESPO2EL"
	},
	{
		"accountId": 202374952,
		"revisionDate": 1510948916000,
		"summonerLevel": 30,
		"id": 4251569,
		"profileIconId": 2098,
		"name": "Z0mbieW"
	},
	{
		"accountId": 201263779,
		"revisionDate": 1511429888000,
		"summonerLevel": 33,
		"id": 3164901,
		"profileIconId": 3186,
		"name": "Dfoguel"
	},
	{
		"accountId": 200781379,
		"revisionDate": 1511464597000,
		"summonerLevel": 33,
		"id": 2567869,
		"profileIconId": 3186,
		"name": "Cer\u00f3l De Areia"
	},
	{
		"accountId": 411267,
		"revisionDate": 1511425368000,
		"summonerLevel": 30,
		"id": 476367,
		"profileIconId": 3171,
		"name": "PkGunts"
	},
	{
		"accountId": 201585890,
		"revisionDate": 1511094883000,
		"summonerLevel": 30,
		"id": 3501464,
		"profileIconId": 1109,
		"name": "Nalbina"
	},
	{
		"accountId": 628126,
		"revisionDate": 1495754839000,
		"summonerLevel": 30,
		"id": 624258,
		"profileIconId": 1386,
		"name": "Jannaconda"
	},
	{
		"accountId": 201264961,
		"revisionDate": 1511090739000,
		"summonerLevel": 32,
		"id": 3135181,
		"profileIconId": 6,
		"name": "Mamae Do Houg"
	},
	{
		"accountId": 209334050,
		"revisionDate": 1511475213000,
		"summonerLevel": 42,
		"id": 13725049,
		"profileIconId": 1230,
		"name": "Bytee"
	},
	{
		"accountId": 1291254,
		"revisionDate": 1495754935000,
		"summonerLevel": 30,
		"id": 1414188,
		"profileIconId": 1154,
		"name": "LaTexuGo"
	},
	{
		"accountId": 202765735,
		"revisionDate": 1511435626000,
		"summonerLevel": 35,
		"id": 4717212,
		"profileIconId": 912,
		"name": "sutsca"
	},
	{
		"accountId": 202368112,
		"revisionDate": 1511111766000,
		"summonerLevel": 34,
		"id": 4310747,
		"profileIconId": 1644,
		"name": "Only ARAM Game"
	},
	{
		"accountId": 214124146,
		"revisionDate": 1511365936000,
		"summonerLevel": 30,
		"id": 23050829,
		"profileIconId": 3015,
		"name": "meclesutra"
	},
	{
		"accountId": 200423007,
		"revisionDate": 1495755299000,
		"summonerLevel": 30,
		"id": 2258709,
		"profileIconId": 1378,
		"name": "Erva Green"
	},
	{
		"accountId": 200721995,
		"revisionDate": 1511514259000,
		"summonerLevel": 42,
		"id": 2561043,
		"profileIconId": 3186,
		"name": "Myuw"
	},
	{
		"accountId": 201690086,
		"revisionDate": 1500637940000,
		"summonerLevel": 30,
		"id": 3633766,
		"profileIconId": 953,
		"name": "BoomerBlast"
	},
	{
		"accountId": 203250090,
		"revisionDate": 1510480780000,
		"summonerLevel": 30,
		"id": 5243563,
		"profileIconId": 1436,
		"name": "PequenoAprendiz"
	},
	{
		"accountId": 201104708,
		"revisionDate": 1510767998000,
		"summonerLevel": 35,
		"id": 2977429,
		"profileIconId": 18,
		"name": "abib"
	},
	{
		"accountId": 1225125,
		"revisionDate": 1507820222000,
		"summonerLevel": 30,
		"id": 1324835,
		"profileIconId": 503,
		"name": "M7 D K"
	},
	{
		"accountId": 203743634,
		"revisionDate": 1511200198000,
		"summonerLevel": 30,
		"id": 5845086,
		"profileIconId": 3155,
		"name": "iPlum"
	},
	{
		"accountId": 201929454,
		"revisionDate": 1508112481000,
		"summonerLevel": 30,
		"id": 3852284,
		"profileIconId": 2087,
		"name": "zerinhoplays"
	},
	{
		"accountId": 514729,
		"revisionDate": 1506057283000,
		"summonerLevel": 30,
		"id": 589829,
		"profileIconId": 1642,
		"name": "homem regular"
	},
	{
		"accountId": 207922858,
		"revisionDate": 1509035469000,
		"summonerLevel": 30,
		"id": 11778716,
		"profileIconId": 3015,
		"name": "Death Note"
	},
	{
		"accountId": 1694713,
		"revisionDate": 1511173496000,
		"summonerLevel": 32,
		"id": 1795649,
		"profileIconId": 1391,
		"name": "JDTELESBR"
	},
	{
		"accountId": 202091065,
		"revisionDate": 1511335872000,
		"summonerLevel": 34,
		"id": 3964371,
		"profileIconId": 1109,
		"name": "lauretti"
	},
	{
		"accountId": 1522373,
		"revisionDate": 1510222667000,
		"summonerLevel": 30,
		"id": 1653740,
		"profileIconId": 1594,
		"name": "o0COAN0o"
	},
	{
		"accountId": 200703987,
		"revisionDate": 1511356466000,
		"summonerLevel": 30,
		"id": 2509452,
		"profileIconId": 1633,
		"name": "XPlatinuM"
	},
	{
		"accountId": 368066,
		"revisionDate": 1510674038000,
		"summonerLevel": 30,
		"id": 403166,
		"profileIconId": 2088,
		"name": "Frogzord"
	},
	{
		"accountId": 201450500,
		"revisionDate": 1495755592000,
		"summonerLevel": 30,
		"id": 3326066,
		"profileIconId": 7,
		"name": "Th\u00ea Phenom"
	},
	{
		"accountId": 983213,
		"revisionDate": 1511515601000,
		"summonerLevel": 35,
		"id": 1082349,
		"profileIconId": 3186,
		"name": "FredMeirelles"
	},
	{
		"accountId": 1250785,
		"revisionDate": 1511520273000,
		"summonerLevel": 32,
		"id": 1420968,
		"profileIconId": 3186,
		"name": "Arcangel777"
	},
	{
		"accountId": 473201,
		"revisionDate": 1509036451000,
		"summonerLevel": 30,
		"id": 514793,
		"profileIconId": 538,
		"name": "taliyah op"
	},
	{
		"accountId": 201737539,
		"revisionDate": 1510424428000,
		"summonerLevel": 32,
		"id": 3619839,
		"profileIconId": 660,
		"name": "Alaricc"
	},
	{
		"accountId": 205229009,
		"revisionDate": 1511518278000,
		"summonerLevel": 32,
		"id": 9291948,
		"profileIconId": 3186,
		"name": "CADE MEU CAF\u00c9"
	},
	{
		"accountId": 910183,
		"revisionDate": 1511362603000,
		"summonerLevel": 30,
		"id": 973949,
		"profileIconId": 3009,
		"name": "LucaslFarsura"
	},
	{
		"accountId": 405357,
		"revisionDate": 1510583257000,
		"summonerLevel": 30,
		"id": 470457,
		"profileIconId": 1301,
		"name": "Moskytu"
	},
	{
		"accountId": 897789,
		"revisionDate": 1501019245000,
		"summonerLevel": 30,
		"id": 992889,
		"profileIconId": 10,
		"name": "Leopodla"
	},
	{
		"accountId": 203056029,
		"revisionDate": 1508946680000,
		"summonerLevel": 30,
		"id": 5113093,
		"profileIconId": 714,
		"name": "Machomemoo"
	},
	{
		"accountId": 349994,
		"revisionDate": 1511510796000,
		"summonerLevel": 35,
		"id": 421390,
		"profileIconId": 3186,
		"name": "Fritadoidao"
	},
	{
		"accountId": 200003538,
		"revisionDate": 1511509053000,
		"summonerLevel": 32,
		"id": 1860461,
		"profileIconId": 3186,
		"name": "LadyKim"
	},
	{
		"accountId": 201540825,
		"revisionDate": 1509451540000,
		"summonerLevel": 30,
		"id": 3406107,
		"profileIconId": 1624,
		"name": "GameOwner"
	},
	{
		"accountId": 210978793,
		"revisionDate": 1495756931000,
		"summonerLevel": 30,
		"id": 16890575,
		"profileIconId": 1598,
		"name": "MarcoslNGSMV"
	},
	{
		"accountId": 213816282,
		"revisionDate": 1511452337000,
		"summonerLevel": 37,
		"id": 22612464,
		"profileIconId": 3186,
		"name": "K O R O Z Z"
	},
	{
		"accountId": 202209333,
		"revisionDate": 1511518872000,
		"summonerLevel": 39,
		"id": 4065803,
		"profileIconId": 3186,
		"name": "Killer geek"
	},
	{
		"accountId": 200705062,
		"revisionDate": 1511502055000,
		"summonerLevel": 31,
		"id": 2478749,
		"profileIconId": 3186,
		"name": "Fiodifafa"
	},
	{
		"accountId": 204013789,
		"revisionDate": 1511156474000,
		"summonerLevel": 33,
		"id": 6475039,
		"profileIconId": 3008,
		"name": "To IndGNARdo"
	},
	{
		"accountId": 205575540,
		"revisionDate": 1511451303000,
		"summonerLevel": 38,
		"id": 9402178,
		"profileIconId": 3186,
		"name": "CaaF BieL"
	},
	{
		"accountId": 206192389,
		"revisionDate": 1508857488000,
		"summonerLevel": 30,
		"id": 10046466,
		"profileIconId": 907,
		"name": "KamuiHunt"
	},
	{
		"accountId": 204702671,
		"revisionDate": 1510208482000,
		"summonerLevel": 30,
		"id": 7634807,
		"profileIconId": 673,
		"name": "Gabriel KNZ"
	},
	{
		"accountId": 203304731,
		"revisionDate": 1508234420000,
		"summonerLevel": 30,
		"id": 5370341,
		"profileIconId": 978,
		"name": "Crow0201"
	},
	{
		"accountId": 201826219,
		"revisionDate": 1504810376000,
		"summonerLevel": 30,
		"id": 3730606,
		"profileIconId": 1670,
		"name": "NaTesTaxD"
	},
	{
		"accountId": 205913151,
		"revisionDate": 1510913053000,
		"summonerLevel": 31,
		"id": 9812921,
		"profileIconId": 3158,
		"name": "Pernoite"
	},
	{
		"accountId": 200900497,
		"revisionDate": 1511514530000,
		"summonerLevel": 33,
		"id": 2814221,
		"profileIconId": 3186,
		"name": "Myron Arth"
	},
	{
		"accountId": 210541483,
		"revisionDate": 1498770966000,
		"summonerLevel": 30,
		"id": 16240131,
		"profileIconId": 1644,
		"name": "its my shadow"
	},
	{
		"accountId": 202137459,
		"revisionDate": 1511458386000,
		"summonerLevel": 34,
		"id": 3988590,
		"profileIconId": 3186,
		"name": "Sr Psicologo "
	},
	{
		"accountId": 404482,
		"revisionDate": 1510692234000,
		"summonerLevel": 31,
		"id": 459582,
		"profileIconId": 3158,
		"name": "JooN EL Rayo"
	},
	{
		"accountId": 211110511,
		"revisionDate": 1495756953000,
		"summonerLevel": 30,
		"id": 17141445,
		"profileIconId": 1301,
		"name": "Felipekwc"
	},
	{
		"accountId": 634138,
		"revisionDate": 1495754840000,
		"summonerLevel": 30,
		"id": 625388,
		"profileIconId": 537,
		"name": "TSM TheLoneOne"
	},
	{
		"accountId": 1560694,
		"revisionDate": 1511442232000,
		"summonerLevel": 35,
		"id": 1628466,
		"profileIconId": 1225,
		"name": "Mdragnel"
	},
	{
		"accountId": 1091984,
		"revisionDate": 1495754903000,
		"summonerLevel": 30,
		"id": 1207040,
		"profileIconId": 1598,
		"name": "MAGlN Borges"
	},
	{
		"accountId": 204054189,
		"revisionDate": 1511453305000,
		"summonerLevel": 37,
		"id": 6641695,
		"profileIconId": 1232,
		"name": "Caro\u00e7o"
	},
	{
		"accountId": 204264426,
		"revisionDate": 1511294574000,
		"summonerLevel": 37,
		"id": 6843936,
		"profileIconId": 1427,
		"name": "MegumiShimizu"
	},
	{
		"accountId": 202810410,
		"revisionDate": 1511429384000,
		"summonerLevel": 35,
		"id": 4841138,
		"profileIconId": 3186,
		"name": "IImineiroII"
	},
	{
		"accountId": 209747054,
		"revisionDate": 1499342143000,
		"summonerLevel": 30,
		"id": 14523681,
		"profileIconId": 1114,
		"name": "Sr Detogni"
	},
	{
		"accountId": 1539432,
		"revisionDate": 1511510029000,
		"summonerLevel": 36,
		"id": 1655578,
		"profileIconId": 3186,
		"name": "AlexandreMoreira"
	},
	{
		"accountId": 202959272,
		"revisionDate": 1511461595000,
		"summonerLevel": 37,
		"id": 4876438,
		"profileIconId": 3186,
		"name": "J\u00e1 Nasci Tiltado"
	},
	{
		"accountId": 204337158,
		"revisionDate": 1509903608000,
		"summonerLevel": 30,
		"id": 6991436,
		"profileIconId": 2090,
		"name": "Hellgorakk"
	},
	{
		"accountId": 921048,
		"revisionDate": 1506573459000,
		"summonerLevel": 30,
		"id": 924297,
		"profileIconId": 1458,
		"name": "magicwow1"
	},
	{
		"accountId": 204512989,
		"revisionDate": 1511518900000,
		"summonerLevel": 30,
		"id": 7362248,
		"profileIconId": 2087,
		"name": "ArturIchigo"
	},
	{
		"accountId": 200244510,
		"revisionDate": 1511455759000,
		"summonerLevel": 39,
		"id": 1989616,
		"profileIconId": 3186,
		"name": "MatadorCelestial"
	},
	{
		"accountId": 1093083,
		"revisionDate": 1511497862000,
		"summonerLevel": 31,
		"id": 1197392,
		"profileIconId": 3186,
		"name": "Havaiianas"
	},
	{
		"accountId": 1553097,
		"revisionDate": 1510813727000,
		"summonerLevel": 33,
		"id": 1646547,
		"profileIconId": 1297,
		"name": "lRokanl"
	},
	{
		"accountId": 527335,
		"revisionDate": 1495754820000,
		"summonerLevel": 30,
		"id": 425782,
		"profileIconId": 787,
		"name": "miller16"
	},
	{
		"accountId": 209959027,
		"revisionDate": 1510420065000,
		"summonerLevel": 30,
		"id": 15070134,
		"profileIconId": 3006,
		"name": "sharp222"
	},
	{
		"accountId": 203975489,
		"revisionDate": 1511115045000,
		"summonerLevel": 35,
		"id": 6423189,
		"profileIconId": 3157,
		"name": "CHUTO OTAKUS"
	},
	{
		"accountId": 204813228,
		"revisionDate": 1504473803000,
		"summonerLevel": 30,
		"id": 7900232,
		"profileIconId": 1401,
		"name": "T0C4T3RR0"
	},
	{
		"accountId": 203971497,
		"revisionDate": 1508510760000,
		"summonerLevel": 30,
		"id": 6362976,
		"profileIconId": 616,
		"name": "IHensh"
	},
	{
		"accountId": 202086649,
		"revisionDate": 1511404548000,
		"summonerLevel": 34,
		"id": 3973878,
		"profileIconId": 2089,
		"name": "VITALINO UCHIHA"
	},
	{
		"accountId": 205413757,
		"revisionDate": 1511504270000,
		"summonerLevel": 37,
		"id": 9321719,
		"profileIconId": 3186,
		"name": "confuso dest"
	},
	{
		"accountId": 200819588,
		"revisionDate": 1511466450000,
		"summonerLevel": 32,
		"id": 2613931,
		"profileIconId": 3186,
		"name": "Zaramothy"
	},
	{
		"accountId": 201112617,
		"revisionDate": 1501100995000,
		"summonerLevel": 30,
		"id": 3534678,
		"profileIconId": 1391,
		"name": "CordeiroBacon"
	},
	{
		"accountId": 201867991,
		"revisionDate": 1511012892000,
		"summonerLevel": 31,
		"id": 3774653,
		"profileIconId": 1642,
		"name": "CaaF Zirtec"
	},
	{
		"accountId": 201719390,
		"revisionDate": 1511357822000,
		"summonerLevel": 34,
		"id": 3637187,
		"profileIconId": 685,
		"name": "RED H00D"
	},
	{
		"accountId": 200702778,
		"revisionDate": 1511463167000,
		"summonerLevel": 32,
		"id": 2488614,
		"profileIconId": 3186,
		"name": "KuroJNX"
	},
	{
		"accountId": 201543070,
		"revisionDate": 1503644378000,
		"summonerLevel": 30,
		"id": 3436280,
		"profileIconId": 578,
		"name": "HTXD99"
	},
	{
		"accountId": 387117,
		"revisionDate": 1505765727000,
		"summonerLevel": 30,
		"id": 442217,
		"profileIconId": 507,
		"name": "pepe xD"
	},
	{
		"accountId": 210360700,
		"revisionDate": 1510584302000,
		"summonerLevel": 30,
		"id": 15812886,
		"profileIconId": 1401,
		"name": "D4rk s2 Starkee "
	},
	{
		"accountId": 1715307,
		"revisionDate": 1511457878000,
		"summonerLevel": 35,
		"id": 1774970,
		"profileIconId": 3186,
		"name": "TimKiller95"
	},
	{
		"accountId": 544852,
		"revisionDate": 1510241972000,
		"summonerLevel": 30,
		"id": 467972,
		"profileIconId": 518,
		"name": "Bolad\u00e3o de \u00c1moR"
	},
	{
		"accountId": 1011105,
		"revisionDate": 1511520126000,
		"summonerLevel": 40,
		"id": 1134338,
		"profileIconId": 3186,
		"name": "Gus a Fada"
	},
	{
		"accountId": 200698367,
		"revisionDate": 1511286723000,
		"summonerLevel": 32,
		"id": 2517972,
		"profileIconId": 546,
		"name": "Horus eye"
	},
	{
		"accountId": 205351842,
		"revisionDate": 1511512563000,
		"summonerLevel": 31,
		"id": 9015845,
		"profileIconId": 3186,
		"name": "Sr KyoraKu"
	},
	{
		"accountId": 201095785,
		"revisionDate": 1511473931000,
		"summonerLevel": 36,
		"id": 2956434,
		"profileIconId": 3186,
		"name": "Calvs"
	},
	{
		"accountId": 205087598,
		"revisionDate": 1511369106000,
		"summonerLevel": 36,
		"id": 8395504,
		"profileIconId": 3186,
		"name": "itachS"
	},
	{
		"accountId": 214211535,
		"revisionDate": 1511519888000,
		"summonerLevel": 36,
		"id": 23045603,
		"profileIconId": 3,
		"name": "MLn mito"
	},
	{
		"accountId": 1028100,
		"revisionDate": 1507811985000,
		"summonerLevel": 30,
		"id": 1170914,
		"profileIconId": 539,
		"name": "ImMessiah"
	},
	{
		"accountId": 650798,
		"revisionDate": 1509804081000,
		"summonerLevel": 30,
		"id": 3502826,
		"profileIconId": 3006,
		"name": "XxSceneLord"
	},
	{
		"accountId": 448000,
		"revisionDate": 1511386319000,
		"summonerLevel": 32,
		"id": 543100,
		"profileIconId": 3186,
		"name": "CaaF Halls"
	},
	{
		"accountId": 200898104,
		"revisionDate": 1510694855000,
		"summonerLevel": 30,
		"id": 2833714,
		"profileIconId": 575,
		"name": "YakuzaTwO"
	},
	{
		"accountId": 208897532,
		"revisionDate": 1511508535000,
		"summonerLevel": 35,
		"id": 13089902,
		"profileIconId": 3186,
		"name": "Call Me Ayato"
	},
	{
		"accountId": 1488613,
		"revisionDate": 1510784756000,
		"summonerLevel": 30,
		"id": 1650962,
		"profileIconId": 502,
		"name": "RnG PolgaDre"
	},
	{
		"accountId": 202855880,
		"revisionDate": 1511362316000,
		"summonerLevel": 32,
		"id": 4825173,
		"profileIconId": 3158,
		"name": "RedMaster555"
	},
	{
		"accountId": 920435,
		"revisionDate": 1511448735000,
		"summonerLevel": 33,
		"id": 934000,
		"profileIconId": 1585,
		"name": "god in my corner"
	},
	{
		"accountId": 210781593,
		"revisionDate": 1511451217000,
		"summonerLevel": 35,
		"id": 16571558,
		"profileIconId": 3186,
		"name": "CaaF YakuzA"
	},
	{
		"accountId": 210182286,
		"revisionDate": 1511514378000,
		"summonerLevel": 44,
		"id": 15353443,
		"profileIconId": 3186,
		"name": "Fujyro kutroco"
	},
	{
		"accountId": 202252104,
		"revisionDate": 1511033856000,
		"summonerLevel": 33,
		"id": 4170359,
		"profileIconId": 591,
		"name": "Fikry"
	},
	{
		"accountId": 201549073,
		"revisionDate": 1511518930000,
		"summonerLevel": 38,
		"id": 3397341,
		"profileIconId": 3186,
		"name": "Titupe"
	},
	{
		"accountId": 1157590,
		"revisionDate": 1510611001000,
		"summonerLevel": 30,
		"id": 1320770,
		"profileIconId": 1113,
		"name": "sTark RX CF"
	},
	{
		"accountId": 201958343,
		"revisionDate": 1503089659000,
		"summonerLevel": 30,
		"id": 3856696,
		"profileIconId": 657,
		"name": "MrCSS"
	},
	{
		"accountId": 209800752,
		"revisionDate": 1511517738000,
		"summonerLevel": 32,
		"id": 14801536,
		"profileIconId": 23,
		"name": "Anivia Dinho"
	},
	{
		"accountId": 201709877,
		"revisionDate": 1511512894000,
		"summonerLevel": 35,
		"id": 3606233,
		"profileIconId": 3186,
		"name": "xXJAIROGIRADEXx"
	},
	{
		"accountId": 200559782,
		"revisionDate": 1511434849000,
		"summonerLevel": 30,
		"id": 2440875,
		"profileIconId": 3006,
		"name": "PolentaGamer"
	},
	{
		"accountId": 201283476,
		"revisionDate": 1510413472000,
		"summonerLevel": 30,
		"id": 3261190,
		"profileIconId": 3009,
		"name": "Chicoball"
	},
	{
		"accountId": 385363,
		"revisionDate": 1510119695000,
		"summonerLevel": 30,
		"id": 440463,
		"profileIconId": 3006,
		"name": "FlyMaker"
	},
	{
		"accountId": 1546353,
		"revisionDate": 1509719368000,
		"summonerLevel": 30,
		"id": 1629301,
		"profileIconId": 3006,
		"name": "SuricatoSelvagem"
	},
	{
		"accountId": 1068238,
		"revisionDate": 1511360513000,
		"summonerLevel": 33,
		"id": 1163534,
		"profileIconId": 3186,
		"name": "Novelli"
	},
	{
		"accountId": 202459236,
		"revisionDate": 1503945772000,
		"summonerLevel": 30,
		"id": 4337914,
		"profileIconId": 1398,
		"name": "Almirante Mello"
	},
	{
		"accountId": 201134718,
		"revisionDate": 1511205291000,
		"summonerLevel": 32,
		"id": 3001275,
		"profileIconId": 654,
		"name": "Brenomf"
	},
	{
		"accountId": 202548247,
		"revisionDate": 1511520522000,
		"summonerLevel": 33,
		"id": 4436362,
		"profileIconId": 3186,
		"name": "DontTouchMyCarry"
	},
	{
		"accountId": 200977990,
		"revisionDate": 1511463735000,
		"summonerLevel": 37,
		"id": 2903233,
		"profileIconId": 3186,
		"name": "BRND b0s3"
	},
	{
		"accountId": 200431352,
		"revisionDate": 1507961420000,
		"summonerLevel": 30,
		"id": 2249105,
		"profileIconId": 1644,
		"name": "The Phenom SL"
	},
	{
		"accountId": 203172703,
		"revisionDate": 1511155330000,
		"summonerLevel": 35,
		"id": 5215869,
		"profileIconId": 589,
		"name": "Petenucci"
	},
	{
		"accountId": 203142857,
		"revisionDate": 1510415158000,
		"summonerLevel": 30,
		"id": 5143184,
		"profileIconId": 3006,
		"name": "xXlaurettiXx"
	},
	{
		"accountId": 207957513,
		"revisionDate": 1509275557000,
		"summonerLevel": 30,
		"id": 11970173,
		"profileIconId": 1665,
		"name": "TheRealPixinine"
	},
	{
		"accountId": 539667,
		"revisionDate": 1511427972000,
		"summonerLevel": 34,
		"id": 507000,
		"profileIconId": 3186,
		"name": "warLOOK"
	},
	{
		"accountId": 448239,
		"revisionDate": 1511410319000,
		"summonerLevel": 32,
		"id": 543339,
		"profileIconId": 3158,
		"name": "EvilKing"
	},
	{
		"accountId": 1535800,
		"revisionDate": 1495754991000,
		"summonerLevel": 30,
		"id": 1654635,
		"profileIconId": 1385,
		"name": "Colin        xxx"
	},
	{
		"accountId": 201683382,
		"revisionDate": 1509974495000,
		"summonerLevel": 30,
		"id": 3613982,
		"profileIconId": 714,
		"name": "EvilFace"
	},
	{
		"accountId": 200341901,
		"revisionDate": 1510652334000,
		"summonerLevel": 30,
		"id": 2153347,
		"profileIconId": 682,
		"name": "Hi im bei\u00e7o"
	},
	{
		"accountId": 388835,
		"revisionDate": 1510602444000,
		"summonerLevel": 30,
		"id": 443935,
		"profileIconId": 3004,
		"name": "Trojax"
	},
	{
		"accountId": 203981411,
		"revisionDate": 1511519254000,
		"summonerLevel": 36,
		"id": 6323482,
		"profileIconId": 3186,
		"name": "TheKingOf12"
	},
	{
		"accountId": 202790403,
		"revisionDate": 1500447835000,
		"summonerLevel": 30,
		"id": 4689465,
		"profileIconId": 1598,
		"name": "Arthoriius"
	},
	{
		"accountId": 200803765,
		"revisionDate": 1510304530000,
		"summonerLevel": 30,
		"id": 5653406,
		"profileIconId": 3008,
		"name": "Bruxao the cat"
	},
	{
		"accountId": 200876252,
		"revisionDate": 1511348372000,
		"summonerLevel": 33,
		"id": 2830983,
		"profileIconId": 3186,
		"name": "Jandersoms"
	},
	{
		"accountId": 206442375,
		"revisionDate": 1495756339000,
		"summonerLevel": 30,
		"id": 10297123,
		"profileIconId": 1598,
		"name": "Adelino2"
	},
	{
		"accountId": 204061075,
		"revisionDate": 1511518185000,
		"summonerLevel": 48,
		"id": 6642073,
		"profileIconId": 3025,
		"name": "StormTro0per"
	},
	{
		"accountId": 208255453,
		"revisionDate": 1511455503000,
		"summonerLevel": 33,
		"id": 12216957,
		"profileIconId": 3193,
		"name": "yN HisoKa"
	},
	{
		"accountId": 210445513,
		"revisionDate": 1511462672000,
		"summonerLevel": 41,
		"id": 15931770,
		"profileIconId": 3186,
		"name": "R hiarleymm"
	},
	{
		"accountId": 762941,
		"revisionDate": 1511263990000,
		"summonerLevel": 31,
		"id": 787835,
		"profileIconId": 3167,
		"name": "Oxygenon"
	},
	{
		"accountId": 1090125,
		"revisionDate": 1511510826000,
		"summonerLevel": 35,
		"id": 1186719,
		"profileIconId": 617,
		"name": "Rafiusk10"
	},
	{
		"accountId": 200452274,
		"revisionDate": 1511518276000,
		"summonerLevel": 37,
		"id": 2301363,
		"profileIconId": 1438,
		"name": "PetyS2"
	},
	{
		"accountId": 1490667,
		"revisionDate": 1511517317000,
		"summonerLevel": 40,
		"id": 1641510,
		"profileIconId": 1231,
		"name": "FOl INTENSO FOI"
	},
	{
		"accountId": 207966950,
		"revisionDate": 1503579138000,
		"summonerLevel": 30,
		"id": 11891231,
		"profileIconId": 1666,
		"name": "Yetik"
	},
	{
		"accountId": 201620446,
		"revisionDate": 1511194084000,
		"summonerLevel": 32,
		"id": 3545571,
		"profileIconId": 1159,
		"name": "Nachbin"
	},
	{
		"accountId": 1038665,
		"revisionDate": 1510926424000,
		"summonerLevel": 31,
		"id": 1191072,
		"profileIconId": 3161,
		"name": "Mefysto"
	},
	{
		"accountId": 201423833,
		"revisionDate": 1495755588000,
		"summonerLevel": 30,
		"id": 3313566,
		"profileIconId": 549,
		"name": "EuFaloSozinho"
	},
	{
		"accountId": 513878,
		"revisionDate": 1495754835000,
		"summonerLevel": 30,
		"id": 588978,
		"profileIconId": 939,
		"name": "X Jon Stark X"
	},
	{
		"accountId": 201019400,
		"revisionDate": 1510145009000,
		"summonerLevel": 30,
		"id": 3773112,
		"profileIconId": 1239,
		"name": "Zelandubas"
	},
	{
		"accountId": 200688862,
		"revisionDate": 1496179055000,
		"summonerLevel": 30,
		"id": 2506825,
		"profileIconId": 2077,
		"name": "bah gg 22K"
	},
	{
		"accountId": 201278752,
		"revisionDate": 1511509542000,
		"summonerLevel": 33,
		"id": 3220979,
		"profileIconId": 3186,
		"name": "MrJony"
	},
	{
		"accountId": 201125230,
		"revisionDate": 1499715308000,
		"summonerLevel": 30,
		"id": 2959926,
		"profileIconId": 681,
		"name": "\u00c7unda"
	},
	{
		"accountId": 1389631,
		"revisionDate": 1511290403000,
		"summonerLevel": 31,
		"id": 1725757,
		"profileIconId": 717,
		"name": "00zymandias"
	},
	{
		"accountId": 200760232,
		"revisionDate": 1511082108000,
		"summonerLevel": 31,
		"id": 2567159,
		"profileIconId": 1425,
		"name": "Cath14"
	},
	{
		"accountId": 201308478,
		"revisionDate": 1511446351000,
		"summonerLevel": 35,
		"id": 3202757,
		"profileIconId": 3186,
		"name": "l Maximvs l"
	},
	{
		"accountId": 895750,
		"revisionDate": 1511349833000,
		"summonerLevel": 31,
		"id": 990850,
		"profileIconId": 3186,
		"name": "Hi im Bugado"
	},
	{
		"accountId": 212173003,
		"revisionDate": 1511456763000,
		"summonerLevel": 32,
		"id": 18883898,
		"profileIconId": 3186,
		"name": "Zuellen Soco"
	},
	{
		"accountId": 212292595,
		"revisionDate": 1510592360000,
		"summonerLevel": 30,
		"id": 19023464,
		"profileIconId": 3194,
		"name": "Galo Embrasado"
	},
	{
		"accountId": 592307,
		"revisionDate": 1495754841000,
		"summonerLevel": 30,
		"id": 632101,
		"profileIconId": 774,
		"name": "TheHgoSkrillex"
	},
	{
		"accountId": 200455664,
		"revisionDate": 1511417263000,
		"summonerLevel": 33,
		"id": 2291715,
		"profileIconId": 666,
		"name": "Mister Keiyor"
	},
	{
		"accountId": 203846446,
		"revisionDate": 1511510916000,
		"summonerLevel": 36,
		"id": 5939804,
		"profileIconId": 3186,
		"name": "Persivaldo"
	},
	{
		"accountId": 200411408,
		"revisionDate": 1510585124000,
		"summonerLevel": 32,
		"id": 2246347,
		"profileIconId": 1625,
		"name": "Eins Zwei Drei"
	},
	{
		"accountId": 200176420,
		"revisionDate": 1511391736000,
		"summonerLevel": 31,
		"id": 1961196,
		"profileIconId": 1598,
		"name": "DihKrust"
	},
	{
		"accountId": 380857,
		"revisionDate": 1511097337000,
		"summonerLevel": 32,
		"id": 415957,
		"profileIconId": 3195,
		"name": "Prestes"
	},
	{
		"accountId": 741664,
		"revisionDate": 1504459975000,
		"summonerLevel": 30,
		"id": 784318,
		"profileIconId": 1404,
		"name": "s de skunK"
	},
	{
		"accountId": 209840657,
		"revisionDate": 1511520215000,
		"summonerLevel": 34,
		"id": 14833399,
		"profileIconId": 3186,
		"name": "NoK4mi"
	}
]